alma_classifier/__init__.py
alma_classifier/bed_utils.py
alma_classifier/cli.py
alma_classifier/config.py
alma_classifier/core.py
alma_classifier/download.py
alma_classifier/ensemble.py
alma_classifier/models.py
alma_classifier/processor.py
alma_classifier/signature.py
alma_classifier/utils.py
alma_classifier-0.2.1.dist-info/licenses/LICENSE.txt
alma_classifier-0.2.1.dist-info/METADATA
alma_classifier-0.2.1.dist-info/WHEEL
alma_classifier-0.2.1.dist-info/entry_points.txt
alma_classifier-0.2.1.dist-info/top_level.txt
alma_classifier-0.2.1.dist-info/RECORD
