Metadata-Version: 2.4
Name: alma-classifier
Version: 0.2.1
Summary: Epigenomic diagnosis of acute leukemia (research use only)
Author-email: Francisco Marchi <francisco@almagenomics.com>
License: GPL-3.0
Keywords: methylation,leukemia,diagnosis
Classifier: Programming Language :: Python :: 3.11
Classifier: License :: OSI Approved :: GNU General Public License v3 (GPLv3)
Classifier: Intended Audience :: Science/Research
Requires-Python: <3.13,>=3.10
License-File: LICENSE.txt
Requires-Dist: numpy<2.0,>=1.25
Requires-Dist: pandas<3.0,>=2.0
Requires-Dist: scikit-learn<1.7.0,>=1.6.1
Requires-Dist: joblib<2.0,>=1.4
Requires-Dist: requests<3.0,>=2.25
Requires-Dist: tqdm<5.0,>=4.60
Provides-Extra: torch
Requires-Dist: torch<3.0,>=2.8; extra == "torch"
Dynamic: license-file
